pymodconn/Decoder_class_layer.py
pymodconn/Encoder_class_layer.py
pymodconn/MHA_block_class_function.py
pymodconn/RNN_block_class_function.py
pymodconn/TCN_addnorm_class_function.py
pymodconn/__init__.py
pymodconn/cit_block.py
pymodconn/keras_tcn.py
pymodconn/model_gen.py
pymodconn/model_gen_utils.py
pymodconn/utils_layers.py
pymodconn/configs/__init__.py
pymodconn/configs/configs_init.py
pymodconn-2.0.0.dist-info/LICENSE
pymodconn-2.0.0.dist-info/METADATA
pymodconn-2.0.0.dist-info/WHEEL
pymodconn-2.0.0.dist-info/top_level.txt
pymodconn-2.0.0.dist-info/RECORD
