Metadata-Version: 2.1
Name: pymodconn
Version: 2.0.0
Summary: Develops sequence to sequence control-oriented deep neural networks in a highly modular way.
Home-page: https://github.com/gaurav306/pymodconn
Author: Gaurav Chaudhary
Author-email: gaurav.chaudhary@ntnu.no
Classifier: Programming Language :: Python :: 3
Classifier: License :: OSI Approved :: MIT License
Classifier: Operating System :: OS Independent
Classifier: Development Status :: 5 - Production/Stable
Classifier: Intended Audience :: Science/Research
Classifier: Topic :: Scientific/Engineering :: Artificial Intelligence
Requires-Python: >=3.7
License-File: LICENSE
